crawltools/__init__.py
crawltools/spider.py
crawltools/utils/__init__.py
crawltools/utils/arguments.py
crawltools/utils/beholder.py
crawltools/utils/executable.py
crawltools/utils/url.py
crawltools/webtoon/__init__.py
crawltools/webtoon/items.py
crawltools/webtoon/middlewares.py
crawltools/webtoon/pipelines.py
crawltools/webtoon/settings.py
crawltools/webtoon/spiders/__init__.py
crawltools/webtoon/spiders/webtoon.py
crawltools-0.1.5.data/scripts/crawler
crawltools-0.1.5.data/scripts/crawler.py
crawltools-0.1.5.dist-info/LICENSE
crawltools-0.1.5.dist-info/METADATA
crawltools-0.1.5.dist-info/WHEEL
crawltools-0.1.5.dist-info/top_level.txt
crawltools-0.1.5.dist-info/RECORD
